checkpoint_sdk/__init__.py
checkpoint_sdk/decoder/__init__.py
checkpoint_sdk/decoder/decoder.py
checkpoint_sdk/decoder/exceptions.py
checkpoint_sdk/transaction/__init__.py
checkpoint_sdk/transaction/exceptions.py
checkpoint_sdk/transaction/transaction.py
checkpoint_sdk/wallet/__init__.py
checkpoint_sdk/wallet/exceptions.py
checkpoint_sdk/wallet/wallet.py
checkpoint_sdk-0.1.1.dist-info/licenses/LICENSE
checkpoint_sdk-0.1.1.dist-info/METADATA
checkpoint_sdk-0.1.1.dist-info/WHEEL
checkpoint_sdk-0.1.1.dist-info/top_level.txt
checkpoint_sdk-0.1.1.dist-info/RECORD
